mi_property_analyser/__init__.py
mi_property_analyser/london_stations.py
mi_property_analyser/station_mapping.py
mi_property_analyser/data/london_stations.csv
mi_property_analyser-0.0.9.dist-info/LICENSE
mi_property_analyser-0.0.9.dist-info/METADATA
mi_property_analyser-0.0.9.dist-info/WHEEL
mi_property_analyser-0.0.9.dist-info/top_level.txt
mi_property_analyser-0.0.9.dist-info/RECORD
