Metadata-Version: 2.1
Name: mi-property-analyser
Version: 0.0.9
Summary: First package evs
Home-page: https://github.com/the-code-bae/mi_property_analyser
Author: Maka I
Author-email: nibe12@live.com
License: MIT
Platform: UNKNOWN
Classifier: Programming Language :: Python :: 3
Classifier: License :: OSI Approved :: MIT License
Classifier: Operating System :: OS Independent
Classifier: License :: OSI Approved :: MIT License
Classifier: Programming Language :: Python
Classifier: Programming Language :: Python :: 3.5
Classifier: Programming Language :: Python :: 3.6
Classifier: Programming Language :: Python :: 3.7
Classifier: Topic :: Software Development :: Libraries
Classifier: Topic :: Software Development :: Libraries :: Python Modules
Classifier: Intended Audience :: Developers
Requires-Python: >=3.5
Requires-Dist: asn1crypto (==0.24.0)
Requires-Dist: backcall (==0.1.0)
Requires-Dist: bottleneck (==1.2.1)
Requires-Dist: certifi (==2019.6.16)
Requires-Dist: chardet (==3.0.4)
Requires-Dist: colorama (==0.4.4)
Requires-Dist: cryptography (==2.7)
Requires-Dist: decorator (==4.4.0)
Requires-Dist: geographiclib (==1.50)
Requires-Dist: geopy (==2.1.0)
Requires-Dist: idna (==2.8)
Requires-Dist: ipykernel (==5.1.1)
Requires-Dist: ipywidgets (==7.5.0)
Requires-Dist: jedi (==0.13.3)
Requires-Dist: numpy (==1.20.2)
Requires-Dist: pandas (==1.2.4)
Requires-Dist: parso (==0.5.0)
Requires-Dist: pexpect (==4.7.0)
Requires-Dist: pickleshare (==0.7.5)
Requires-Dist: ptyprocess (==0.6.0)
Requires-Dist: pygments (==2.8.1)
Requires-Dist: pytz (==2019.1)
Requires-Dist: requests (==2.24.0)
Requires-Dist: six (==1.15.0)
Requires-Dist: tornado (==6.0.3)
Requires-Dist: traitlets (==4.3.2)
Requires-Dist: urllib3 (==1.24.2)
Requires-Dist: wcwidth (==0.1.7)
